loopsso/__init__.py
loopsso/client.py
src/__init__.py
src/client.py
loopsso-0.0.2.dist-info/LICENSE
loopsso-0.0.2.dist-info/METADATA
loopsso-0.0.2.dist-info/WHEEL
loopsso-0.0.2.dist-info/top_level.txt
loopsso-0.0.2.dist-info/RECORD
