Metadata-Version: 2.1
Name: loopsso
Version: 0.0.2
Summary: Api client for loops.so
Author: Omar Faruk Riyad
Author-email: <omfriyad@gmail.com>
Keywords: python,loops.so,api
Classifier: Development Status :: 1 - Planning
Classifier: Intended Audience :: Developers
Classifier: Programming Language :: Python :: 3.5
Classifier: Programming Language :: Python :: 3.6
Classifier: Programming Language :: Python :: 3.7
Classifier: Programming Language :: Python :: 3.8
Classifier: Operating System :: Unix
Classifier: Operating System :: MacOS :: MacOS X
Classifier: Operating System :: Microsoft :: Windows
License-File: LICENSE
Requires-Dist: requests
